mcp_ocr/__init__.py
mcp_ocr/__main__.py
mcp_ocr/install_tesseract.py
mcp_ocr/server.py
mcp_ocr-0.1.4.dist-info/METADATA
mcp_ocr-0.1.4.dist-info/WHEEL
mcp_ocr-0.1.4.dist-info/entry_points.txt
mcp_ocr-0.1.4.dist-info/licenses/LICENSE
mcp_ocr-0.1.4.dist-info/RECORD
