Metadata-Version: 2.4
Name: mcp-ocr
Version: 0.1.4
Summary: MCP server for OCR functionality using Tesseract
Project-URL: Homepage, https://github.com/yourusername/mcp-ocr
Project-URL: Documentation, https://github.com/yourusername/mcp-ocr#readme
Project-URL: Issues, https://github.com/yourusername/mcp-ocr/issues
Author-email: Rajan Shukla <rshukla2k@gmail.com>
License: MIT
License-File: LICENSE
Classifier: Development Status :: 4 - Beta
Classifier: Environment :: Console
Classifier: Intended Audience :: Developers
Classifier: License :: OSI Approved :: MIT License
Classifier: Operating System :: OS Independent
Classifier: Programming Language :: Python :: 3
Classifier: Programming Language :: Python :: 3.11
Classifier: Topic :: Software Development :: Libraries :: Python Modules
Requires-Python: >=3.11
Requires-Dist: httpx>=0.24.0
Requires-Dist: mcp[cli]>=1.2.0
Requires-Dist: numpy>=1.24.0
Requires-Dist: opencv-python>=4.8.0
Requires-Dist: pdf2image>=1.17.0
Requires-Dist: pillow>=10.0.0
Requires-Dist: pytesseract>=0.3.10
Provides-Extra: test
Requires-Dist: pytest-asyncio>=0.21.0; extra == 'test'
Requires-Dist: pytest-cov>=4.0.0; extra == 'test'
Requires-Dist: pytest>=7.0.0; extra == 'test'
